Dabas/__init__.py
Dabas/_data.py
Dabas/_factory.py
Dabas/_manager.py
dabas-1.0.5.dist-info/licenses/LICENSE
dabas-1.0.5.dist-info/METADATA
dabas-1.0.5.dist-info/WHEEL
dabas-1.0.5.dist-info/top_level.txt
dabas-1.0.5.dist-info/RECORD
