Metadata-Version: 2.4
Name: Dabas
Version: 1.0.5
Summary: A Python library for Database Management
Home-page: https://github.com/abbas-bachari/Dabas
Author: Abbas Bachari
Author-email: abbas-bachari@hotmail.com
License: MIT
Project-URL: Homepage, https://github.com/abbas-bachari/Dabas
Project-URL: Documentation, https://github.com/abbas-bachari/Dabas
Project-URL: Source, https://github.com/abbas-bachari/Dabas/
Project-URL: Tracker, https://github.com/abbas-bachari/Dabas/issues
Keywords: Dabas,Database,Database-Management,Dabas-python,SQLAlchemy,SQLAlchemy-python,Dabas-SQLAlchemy,Dabas-SQLAlchemy-python,SQLAlchemy-Database-Management
Classifier: Intended Audience :: Developers
Classifier: Intended Audience :: Financial and Insurance Industry
Classifier: Topic :: Software Development :: Libraries :: Python Modules
Classifier: Operating System :: OS Independent
Classifier: Programming Language :: Python :: 3
Requires-Python: >=3.8
License-File: LICENSE
Requires-Dist: SQLAlchemy>=1.4
Dynamic: author
Dynamic: author-email
Dynamic: classifier
Dynamic: description
Dynamic: description-content-type
Dynamic: home-page
Dynamic: keywords
Dynamic: license
Dynamic: license-file
Dynamic: project-url
Dynamic: requires-dist
Dynamic: requires-python
Dynamic: summary
